MANIFEST.in
README.txt
setup.cfg
setup.py
c2/__init__.py
c2.patch.plone3mail.egg-info/PKG-INFO
c2.patch.plone3mail.egg-info/SOURCES.txt
c2.patch.plone3mail.egg-info/dependency_links.txt
c2.patch.plone3mail.egg-info/entry_points.txt
c2.patch.plone3mail.egg-info/namespace_packages.txt
c2.patch.plone3mail.egg-info/not-zip-safe
c2.patch.plone3mail.egg-info/requires.txt
c2.patch.plone3mail.egg-info/top_level.txt
c2/patch/__init__.py
c2/patch/plone3mail/HotfixRegistrationTool.py
c2/patch/plone3mail/HotfixSecureMailHost.py
c2/patch/plone3mail/__init__.py
c2/patch/plone3mail/configure.zcml
c2/patch/plone3mail/tests.py
c2/patch/plone3mail/version.txt
docs/HISTORY.txt
docs/INSTALL.txt
docs/LICENSE.GPL
docs/LICENSE.txt