Metadata-Version: 1.0
Name: c2.patch.plone3mail
Version: 0.2
Summary: Patches for Plone 3.x, multi-language bug of mail header
Home-page: http://www.cmscom.jp
Author: Manabu Terada
Author-email: terada@cmscom.jp
License: GPL
Keywords: plone patch mail
Platform: UNKNOWN
Classifier: Framework :: Plone
Classifier: Programming Language :: Python
Classifier: Topic :: Software Development :: Libraries :: Python Modules
